stdz/__init__.py
stdz/foo.csv
stdz-0.0.1.dist-info/LICENSE
stdz-0.0.1.dist-info/WHEEL
stdz-0.0.1.dist-info/METADATA
stdz-0.0.1.dist-info/RECORD
