Metadata-Version: 2.1
Name: stdz
Version: 0.0.1
Summary: Standardize stable isotope measurements by comparison with reference materials of known composition
Author-email: Mathieu Daëron <mathieu@daeron.fr>
Requires-Python: >=3.11
Classifier: Programming Language :: Python :: 3
Classifier: License :: OSI Approved :: BSD License
Classifier: Operating System :: OS Independent
Requires-Dist: numpy >=1.24.2
Requires-Dist: pandas >=2.0.0
Requires-Dist: scipy >=1.10.1
Requires-Dist: lmfit >=1.2.2
Project-URL: Home, https://github.com/mdaeron/stdz
